{
  "cli": {
    "version": ">= 10.0.0"
  },
  "build": {
    "development": {
      "developmentClient": true,
      "distribution": "internal"
    },
    "preview": {
      "distribution": "internal",
      "android": {
        "buildType": "apk"
      }
    },
    "preview-pixel": {
      "distribution": "internal",
      "android": {
        "buildType": "apk"
      },
      "env": {
        "ABI_FILTER": "arm64-v8a"
      }
    },
    "production": {}
  },
  "submit": {
    "production": {}
  }
}
